{
  "name": "M_Custom_Theme_Final",
  "component": false,
  "license_url": "https://github.com/mrcoder999/M_Custom_Theme_Final",
  "about_url": "",
  "authors": null,
  "theme_version": null,
  "minimum_discourse_version": null,
  "maximum_discourse_version": null,
  "assets": {
  },
  "color_schemes": {
    "Dracula": {
      "primary": "f2f2f2",
      "secondary": "282a36",
      "tertiary": "bd93f9",
      "quaternary": "8be9fd",
      "header_background": "ffffff",
      "header_primary": "14151f",
      "highlight": "f1fa8c",
      "danger": "ff5555",
      "success": "50fa7b",
      "love": "ff79c6"
    }
  },
  "modifiers": {
  },
  "learn_more": "https://meta.discourse.org/t/beginners-guide-to-using-discourse-themes/91966"
}
